gladier/__init__.py
gladier/base.py
gladier/client.py
gladier/decorators.py
gladier/exc.py
gladier/helpers.py
gladier/state_models.py
gladier/version.py
gladier/managers/__init__.py
gladier/managers/compute_login_manager.py
gladier/managers/compute_manager.py
gladier/managers/flows_manager.py
gladier/managers/login_manager.py
gladier/managers/service_manager.py
gladier/storage/__init__.py
gladier/storage/config.py
gladier/storage/migrations.py
gladier/storage/tokens.py
gladier/tests/__init__.py
gladier/tests/conftest.py
gladier/tests/test_builtin_tools.py
gladier/tests/test_client.py
gladier/tests/test_client_auth.py
gladier/tests/test_client_flow_generation.py
gladier/tests/test_flow_modifiers.py
gladier/tests/test_flow_traversal.py
gladier/tests/test_flows_manager.py
gladier/tests/test_globus_state_models.py
gladier/tests/test_login_manager.py
gladier/tests/test_migrations.py
gladier/tests/test_state_models.py
gladier/tests/test_tool_flow_generation.py
gladier/tests/test_tools.py
gladier/tests/test_utilities.py
gladier/tests/test_data/__init__.py
gladier/tests/test_data/gladier_mocks.py
gladier/tools/__init__.py
gladier/tools/helpers.py
gladier/tools/builtins/__init__.py
gladier/tools/builtins/action.py
gladier/tools/builtins/choice_state.py
gladier/tools/builtins/expression_eval.py
gladier/tools/builtins/fail.py
gladier/tools/builtins/pass_state.py
gladier/tools/builtins/wait.py
gladier/tools/globus/__init__.py
gladier/tools/globus/compute.py
gladier/tools/globus/search.py
gladier/tools/globus/transfer.py
gladier/tools/posix/__init__.py
gladier/tools/posix/shell_cmd.py
gladier/utils/__init__.py
gladier/utils/automate.py
gladier/utils/dynamic_imports.py
gladier/utils/flow_generation.py
gladier/utils/flow_modifiers.py
gladier/utils/flow_traversal.py
gladier/utils/name_generation.py
gladier/utils/pydantic_v1.py
gladier/utils/tool_alias.py
gladier/utils/tool_chain.py
gladier-0.9.6.dist-info/LICENSE
gladier-0.9.6.dist-info/METADATA
gladier-0.9.6.dist-info/WHEEL
gladier-0.9.6.dist-info/top_level.txt
gladier-0.9.6.dist-info/RECORD
