Metadata-Version: 2.2
Name: gladier
Version: 0.9.6
Summary: Tooling for rapid deployment of automation tooling.
Home-page: https://github.com/globus-gladier/gladier
Maintainer: 
Maintainer-email: 
License: Apache 2.0
Classifier: Intended Audience :: Science/Research
Classifier: Intended Audience :: Developers
Classifier: License :: OSI Approved :: Apache Software License
Classifier: Operating System :: POSIX
Classifier: Operating System :: MacOS :: MacOS X
Classifier: Programming Language :: Python
Classifier: Programming Language :: Python :: 3.6
Classifier: Programming Language :: Python :: 3.7
Classifier: Programming Language :: Python :: 3.8
Classifier: Programming Language :: Python :: 3.9
Classifier: Programming Language :: Python :: 3.10
Classifier: Programming Language :: Python :: 3.11
Classifier: Programming Language :: Python :: 3.12
Requires-Python: >=3.6
License-File: LICENSE
Requires-Dist: globus-sdk<4,>=3.46.0
Requires-Dist: globus-compute-sdk<3.0.0,>=2.0.1
Requires-Dist: packaging>=21.3
Requires-Dist: fair-research-login>=0.2.6
Requires-Dist: pydantic>=1.0
Dynamic: classifier
Dynamic: description
Dynamic: description-content-type
Dynamic: home-page
Dynamic: license
Dynamic: requires-dist
Dynamic: requires-python
Dynamic: summary
